csv_parakeet/__init__.py
csv_parakeet/console.py
csv_parakeet-1.1.1.dist-info/LICENSE
csv_parakeet-1.1.1.dist-info/METADATA
csv_parakeet-1.1.1.dist-info/WHEEL
csv_parakeet-1.1.1.dist-info/entry_points.txt
csv_parakeet-1.1.1.dist-info/RECORD
