Metadata-Version: 2.1
Name: csv-parakeet
Version: 1.1.1
Summary: Parquet to CSV command line tool
Home-page: https://github.com/A1fus/csv-parakeet
Author: Alfie Bowman
Author-email: alfiebowman@protonmail.com
Requires-Python: >=3.8.1,<4.0.0
Classifier: Programming Language :: Python :: 3
Classifier: Programming Language :: Python :: 3.9
Classifier: Programming Language :: Python :: 3.10
Classifier: Programming Language :: Python :: 3.11
Requires-Dist: click (>=8.1.3,<9.0.0)
Requires-Dist: pandas (>=2.0.0,<3.0.0)
Requires-Dist: pyarrow (>=12,<14)
Project-URL: Repository, https://github.com/A1fus/csv-parakeet
